smpplib/__init__.py
smpplib/client.py
smpplib/command.py
smpplib/command_codes.py
smpplib/consts.py
smpplib/exceptions.py
smpplib/gsm.py
smpplib/pdu.py
smpplib/ptypes.py
smpplib/smpp.py
smpplib/tests/__init__.py
smpplib/tests/test_client.py
smpplib/tests/test_command.py
smpplib/tests/test_gsm.py
smpplib-2.2.3.dist-info/LICENSE
smpplib-2.2.3.dist-info/METADATA
smpplib-2.2.3.dist-info/WHEEL
smpplib-2.2.3.dist-info/top_level.txt
smpplib-2.2.3.dist-info/zip-safe
smpplib-2.2.3.dist-info/RECORD
